hieralb/__init__.py
hieralb/core.py
hieralb/create_album_files.py
hieralb-0.1.2.dist-info/DESCRIPTION.rst
hieralb-0.1.2.dist-info/METADATA
hieralb-0.1.2.dist-info/RECORD
hieralb-0.1.2.dist-info/WHEEL
hieralb-0.1.2.dist-info/metadata.json
hieralb-0.1.2.dist-info/top_level.txt
