Metadata-Version: 2.0
Name: hieralb
Version: 0.1.2
Summary: Tools for managing hierarchical albums of images.
Home-page: https://github.com/roads/hieralb
Author: Brett D. Roads
Author-email: brett.roads@gmail.com
License: MIT
Platform: UNKNOWN
Classifier: Programming Language :: Python :: 3
Requires-Python: >=3
Requires-Dist: pandas
Requires-Dist: pathlib
Requires-Dist: imageio
